MANIFEST.in
setup.py
ccodeinline/__init__.py
ccodeinline/ccodeinline.py
ccodeinline.egg-info/PKG-INFO
ccodeinline.egg-info/SOURCES.txt
ccodeinline.egg-info/dependency_links.txt
ccodeinline.egg-info/entry_points.txt
ccodeinline.egg-info/requires.txt
ccodeinline.egg-info/top_level.txt
ccodeinline.egg-info/zip-safe