Metadata-Version: 1.1
Name: ccodeinline
Version: 0.0.1
Summary: C/C++ code generation into a more enhanced environement.
Home-page: https://github.com/priendeau/Technical-PorteFolio/tree/master/Python/CCodeInline
Author: Maxiste Deas, Patrick Riendeau
Author-email: maxistedeams@gmail.com
License: OpenBSD
Keywords: ccodeinline
Platform: UNKNOWN
Classifier: Operating System :: OS Independent
Classifier: Programming Language :: Python
Classifier: Topic :: Software Development :: Libraries :: Python Modules
